Metadata-Version: 2.1
Name: efitness-sniper
Version: 0.5
Summary: eFitness.com.pl Booking sniper
Home-page: UNKNOWN
Author: Marek Wajdzik
Author-email: marek@wajdzik.eu
License: MIT
Download-URL: https://github.com/consi/efitness-sniper/archive/0.5.tar.gz
Keywords: efitness,sniper,booking,bookings
Platform: UNKNOWN
Classifier: Development Status :: 4 - Beta
Classifier: Intended Audience :: End Users/Desktop
Classifier: Topic :: Utilities
Classifier: License :: OSI Approved :: MIT License
Classifier: Programming Language :: Python :: 3.7
